{"meta":{"version":1,"code":200,"request":"http://nba.cloud/games/0022000765/boxscore?Format=json","time":"2021-04-05 23:31:14.566171"},"game":{"gameId":"0022000765","gameTimeLocal":"2021-04-05T18:00:00-05:00","gameTimeUTC":"2021-04-05T23:00:00Z","gameTimeHome":"2021-04-05T18:00:00-05:00","gameTimeAway":"2021-04-05T16:00:00-07:00","gameEt":"2021-04-05T19:00:00-04:00","duration":135,"gameCode":"20210405/SACMIN","gameStatusText":"Final","gameStatus":3,"regulationPeriods":4,"period":4,"gameClock":"PT00M00.00S","attendance":1436,"sellout":"0","arena":{"arenaId":61,"arenaName":"Target Center","arenaCity":"Minneapolis","arenaState":"MN","arenaCountry":"US","arenaTimezone":"America/Chicago"},"officials":[{"personId":200833,"name":"Eric Dalen","nameI":"E. Dalen","firstName":"Eric","familyName":"Dalen","jerseyNum":"37","assignment":"OFFICIAL3"},{"personId":201246,"name":"Kevin Cutler","nameI":"K. Cutler","firstName":"Kevin","familyName":"Cutler","jerseyNum":"34","assignment":"OFFICIAL1"},{"personId":203592,"name":"Dedric Taylor","nameI":"D. Taylor","firstName":"Dedric","familyName":"Taylor","jerseyNum":"21","assignment":"OFFICIAL2"}],"homeTeam":{"teamId":1610612750,"teamName":"Timberwolves","teamCity":"Minnesota","teamTricode":"MIN","score":116,"inBonus":"1","timeoutsRemaining":2,"periods":[{"period":1,"periodType":"REGULAR","score":26},{"period":2,"periodType":"REGULAR","score":29},{"period":3,"periodType":"REGULAR","score":27},{"period":4,"periodType":"REGULAR","score":34}],"players":[{"status":"ACTIVE","order":1,"personId":1629006,"jerseyNum":"20","position":"SF","starter":"1","oncourt":"0","played":"1","statistics":{"assists":0,"blocks":0,"blocksReceived":1,"fieldGoalsAttempted":3,"fieldGoalsMade":2,"fieldGoalsPercentage":0.666666666666666,"foulsOffensive":0,"foulsDrawn":1,"foulsPersonal":2,"foulsTechnical":0,"freeThrowsAttempted":2,"freeThrowsMade":2,"freeThrowsPercentage":1.0,"minus":56.0,"minutes":"PT19M31.00S","minutesCalculated":"PT19M","plus":40.0,"plusMinusPoints":-16.0,"points":6,"pointsFastBreak":0,"pointsInThePaint":4,"pointsSecondChance":4,"reboundsDefensive":0,"reboundsOffensive":3,"reboundsTotal":3,"steals":1,"threePointersAttempted":0,"threePointersMade":0,"threePointersPercentage":0.0,"turnovers":0,"twoPointersAttempted":3,"twoPointersMade":2,"twoPointersPercentage":0.666666666666666},"name":"Josh Okogie","nameI":"J. Okogie","firstName":"Josh","familyName":"Okogie"},{"status":"ACTIVE","order":2,"personId":1630183,"jerseyNum":"3","position":"PF","starter":"1","oncourt":"1","played":"1","statistics":{"assists":0,"blocks":1,"blocksReceived":0,"fieldGoalsAttempted":5,"fieldGoalsMade":2,"fieldGoalsPercentage":0.4,"foulsOffensive":0,"foulsDrawn":0,"foulsPersonal":5,"foulsTechnical":0,"freeThrowsAttempted":0,"freeThrowsMade":0,"freeThrowsPercentage":0.0,"minus":53.0,"minutes":"PT19M32.01S","minutesCalculated":"PT19M","plus":49.0,"plusMinusPoints":-4.0,"points":4,"pointsFastBreak":0,"pointsInThePaint":4,"pointsSecondChance":0,"reboundsDefensive":3,"reboundsOffensive":2,"reboundsTotal":5,"steals":0,"threePointersAttempted":1,"threePointersMade":0,"threePointersPercentage":0.0,"turnovers":1,"twoPointersAttempted":4,"twoPointersMade":2,"twoPointersPercentage":0.5},"name":"Jaden McDaniels","nameI":"J. McDaniels","firstName":"Jaden","familyName":"McDaniels"},{"status":"ACTIVE","order":3,"personId":1626157,"jerseyNum":"32","position":"C","starter":"1","oncourt":"1","played":"1","statistics":{"assists":5,"blocks":0,"blocksReceived":2,"fieldGoalsAttempted":18,"fieldGoalsMade":8,"fieldGoalsPercentage":0.444444444444444,"foulsOffensive":1,"foulsDrawn":3,"foulsPersonal":2,"foulsTechnical":0,"freeThrowsAttempted":5,"freeThrowsMade":5,"freeThrowsPercentage":1.0,"minus":87.0,"minutes":"PT36M06.00S","minutesCalculated":"PT36M","plus":89.0,"plusMinusPoints":2.0,"points":23,"pointsFastBreak":0,"pointsInThePaint":10,"pointsSecondChance":5,"reboundsDefensive":9,"reboundsOffensive":4,"reboundsTotal":13,"steals":2,"threePointersAttempted":3,"threePointersMade":2,"threePointersPercentage":0.666666666666666,"turnovers":1,"twoPointersAttempted":15,"twoPointersMade":6,"twoPointersPercentage":0.4},"name":"Karl-Anthony Towns","nameI":"K. Towns","firstName":"Karl-Anthony","familyName":"Towns"},{"status":"ACTIVE","order":4,"personId":1630162,"jerseyNum":"1","position":"SG","starter":"1","oncourt":"1","played":"1","statistics":{"assists":5,"blocks":0,"blocksReceived":2,"fieldGoalsAttempted":15,"fieldGoalsMade":5,"fieldGoalsPercentage":0.333333333333333,"foulsOffensive":0,"foulsDrawn":6,"foulsPersonal":1,"foulsTechnical":0,"freeThrowsAttempted":7,"freeThrowsMade":6,"freeThrowsPercentage":0.857142857142857,"minus":82.0,"minutes":"PT37M33.00S","minutesCalculated":"PT38M","plus":97.0,"plusMinusPoints":15.0,"points":19,"pointsFastBreak":2,"pointsInThePaint":4,"pointsSecondChance":0,"reboundsDefensive":7,"reboundsOffensive":1,"reboundsTotal":8,"steals":2,"threePointersAttempted":10,"threePointersMade":3,"threePointersPercentage":0.3,"turnovers":7,"twoPointersAttempted":5,"twoPointersMade":2,"twoPointersPercentage":0.4},"name":"Anthony Edwards","nameI":"A. Edwards","firstName":"Anthony","familyName":"Edwards"},{"status":"ACTIVE","order":5,"personId":201937,"jerseyNum":"9","position":"PG","starter":"1","oncourt":"1","played":"1","statistics":{"assists":5,"blocks":1,"blocksReceived":0,"fieldGoalsAttempted":5,"fieldGoalsMade":1,"fieldGoalsPercentage":0.2,"foulsOffensive":0,"foulsDrawn":1,"foulsPersonal":1,"foulsTechnical":0,"freeThrowsAttempted":2,"freeThrowsMade":2,"freeThrowsPercentage":1.0,"minus":68.0,"minutes":"PT26M39.00S","minutesCalculated":"PT27M","plus":65.0,"plusMinusPoints":-3.0,"points":4,"pointsFastBreak":2,"pointsInThePaint":2,"pointsSecondChance":0,"reboundsDefensive":1,"reboundsOffensive":0,"reboundsTotal":1,"steals":1,"threePointersAttempted":3,"threePointersMade":0,"threePointersPercentage":0.0,"turnovers":2,"twoPointersAttempted":2,"twoPointersMade":1,"twoPointersPercentage":0.5},"name":"Ricky Rubio","nameI":"R. Rubio","firstName":"Ricky","familyName":"Rubio"},{"status":"ACTIVE","order":6,"personId":1626156,"jerseyNum":"0","starter":"0","oncourt":"1","played":"1","statistics":{"assists":3,"blocks":1,"blocksReceived":1,"fieldGoalsAttempted":19,"fieldGoalsMade":7,"fieldGoalsPercentage":0.368421052631579,"foulsOffensive":0,"foulsDrawn":4,"foulsPersonal":2,"foulsTechnical":0,"freeThrowsAttempted":9,"freeThrowsMade":7,"freeThrowsPercentage":0.777777777777778,"minus":54.0,"minutes":"PT24M28.00S","minutesCalculated":"PT24M","plus":62.0,"plusMinusPoints":8.0,"points":25,"pointsFastBreak":3,"pointsInThePaint":4,"pointsSecondChance":1,"reboundsDefensive":4,"reboundsOffensive":1,"reboundsTotal":5,"steals":1,"threePointersAttempted":7,"threePointersMade":4,"threePointersPercentage":0.5714285714285711,"turnovers":2,"twoPointersAttempted":12,"twoPointersMade":3,"twoPointersPercentage":0.25},"name":"D'Angelo Russell","nameI":"D. Russell","firstName":"D'Angelo","familyName":"Russell"},{"status":"ACTIVE","order":7,"personId":1629162,"jerseyNum":"6","starter":"0","oncourt":"0","played":"1","statistics":{"assists":2,"blocks":0,"blocksReceived":1,"fieldGoalsAttempted":6,"fieldGoalsMade":4,"fieldGoalsPercentage":0.666666666666666,"foulsOffensive":0,"foulsDrawn":0,"foulsPersonal":0,"foulsTechnical":0,"freeThrowsAttempted":0,"freeThrowsMade":0,"freeThrowsPercentage":0.0,"minus":36.0,"minutes":"PT19M45.00S","minutesCalculated":"PT20M","plus":45.0,"plusMinusPoints":9.0,"points":8,"pointsFastBreak":2,"pointsInThePaint":6,"pointsSecondChance":0,"reboundsDefensive":0,"reboundsOffensive":0,"reboundsTotal":0,"steals":0,"threePointersAttempted":1,"threePointersMade":0,"threePointersPercentage":0.0,"turnovers":0,"twoPointersAttempted":5,"twoPointersMade":4,"twoPointersPercentage":0.8},"name":"Jordan McLaughlin","nameI":"J. McLaughlin","firstName":"Jordan","familyName":"McLaughlin"},{"status":"ACTIVE","order":8,"personId":1629633,"jerseyNum":"23","starter":"0","oncourt":"0","played":"1","statistics":{"assists":1,"blocks":0,"blocksReceived":1,"fieldGoalsAttempted":1,"fieldGoalsMade":0,"fieldGoalsPercentage":0.0,"foulsOffensive":0,"foulsDrawn":0,"foulsPersonal":2,"foulsTechnical":0,"freeThrowsAttempted":0,"freeThrowsMade":0,"freeThrowsPercentage":0.0,"minus":14.0,"minutes":"PT06M55.00S","minutesCalculated":"PT07M","plus":9.0,"plusMinusPoints":-5.0,"points":0,"pointsFastBreak":0,"pointsInThePaint":0,"pointsSecondChance":0,"reboundsDefensive":0,"reboundsOffensive":0,"reboundsTotal":0,"steals":0,"threePointersAttempted":0,"threePointersMade":0,"threePointersPercentage":0.0,"turnovers":0,"twoPointersAttempted":1,"twoPointersMade":0,"twoPointersPercentage":0.0},"name":"Jarrett Culver","nameI":"J. Culver","firstName":"Jarrett","familyName":"Culver"},{"status":"ACTIVE","order":9,"personId":1627823,"jerseyNum":"41","starter":"0","oncourt":"0","played":"1","statistics":{"assists":1,"blocks":0,"blocksReceived":0,"fieldGoalsAttempted":10,"fieldGoalsMade":5,"fieldGoalsPercentage":0.5,"foulsOffensive":0,"foulsDrawn":4,"foulsPersonal":0,"foulsTechnical":0,"freeThrowsAttempted":8,"freeThrowsMade":6,"freeThrowsPercentage":0.75,"minus":44.0,"minutes":"PT25M45.00S","minutesCalculated":"PT26M","plus":61.0,"plusMinusPoints":17.0,"points":17,"pointsFastBreak":3,"pointsInThePaint":8,"pointsSecondChance":3,"reboundsDefensive":5,"reboundsOffensive":4,"reboundsTotal":9,"steals":1,"threePointersAttempted":3,"threePointersMade":1,"threePointersPercentage":0.333333333333333,"turnovers":0,"twoPointersAttempted":7,"twoPointersMade":4,"twoPointersPercentage":0.5714285714285711},"name":"Juancho Hernangomez","nameI":"J. Hernangomez","firstName":"Juancho","familyName":"Hernangomez"},{"status":"ACTIVE","order":10,"personId":1629675,"jerseyNum":"11","starter":"0","oncourt":"0","played":"1","statistics":{"assists":0,"blocks":1,"blocksReceived":0,"fieldGoalsAttempted":8,"fieldGoalsMade":4,"fieldGoalsPercentage":0.5,"foulsOffensive":0,"foulsDrawn":0,"foulsPersonal":1,"foulsTechnical":0,"freeThrowsAttempted":0,"freeThrowsMade":0,"freeThrowsPercentage":0.0,"minus":34.0,"minutes":"PT20M48.99S","minutesCalculated":"PT21M","plus":55.0,"plusMinusPoints":21.0,"points":10,"pointsFastBreak":0,"pointsInThePaint":4,"pointsSecondChance":0,"reboundsDefensive":7,"reboundsOffensive":0,"reboundsTotal":7,"steals":1,"threePointersAttempted":3,"threePointersMade":2,"threePointersPercentage":0.666666666666666,"turnovers":0,"twoPointersAttempted":5,"twoPointersMade":2,"twoPointersPercentage":0.4},"name":"Naz Reid","nameI":"N. Reid","firstName":"Naz","familyName":"Reid"},{"status":"ACTIVE","order":11,"personId":1627774,"jerseyNum":"10","starter":"0","oncourt":"0","played":"1","statistics":{"assists":0,"blocks":0,"blocksReceived":0,"fieldGoalsAttempted":1,"fieldGoalsMade":0,"fieldGoalsPercentage":0.0,"foulsOffensive":0,"foulsDrawn":0,"foulsPersonal":0,"foulsTechnical":0,"freeThrowsAttempted":0,"freeThrowsMade":0,"freeThrowsPercentage":0.0,"minus":2.0,"minutes":"PT02M57.00S","minutesCalculated":"PT03M","plus":8.0,"plusMinusPoints":6.0,"points":0,"pointsFastBreak":0,"pointsInThePaint":0,"pointsSecondChance":0,"reboundsDefensive":0,"reboundsOffensive":0,"reboundsTotal":0,"steals":1,"threePointersAttempted":1,"threePointersMade":0,"threePointersPercentage":0.0,"turnovers":1,"twoPointersAttempted":0,"twoPointersMade":0,"twoPointersPercentage":0.0},"name":"Jake Layman","nameI":"J. Layman","firstName":"Jake","familyName":"Layman"},{"status":"ACTIVE","order":12,"personId":202334,"jerseyNum":"17","starter":"0","oncourt":"0","played":"0","statistics":{"assists":0,"blocks":0,"blocksReceived":0,"fieldGoalsAttempted":0,"fieldGoalsMade":0,"fieldGoalsPercentage":0.0,"foulsOffensive":0,"foulsDrawn":0,"foulsPersonal":0,"foulsTechnical":0,"freeThrowsAttempted":0,"freeThrowsMade":0,"freeThrowsPercentage":0.0,"minus":0.0,"minutes":"PT00M00.00S","minutesCalculated":"PT00M","plus":0.0,"plusMinusPoints":0.0,"points":0,"pointsFastBreak":0,"pointsInThePaint":0,"pointsSecondChance":0,"reboundsDefensive":0,"reboundsOffensive":0,"reboundsTotal":0,"steals":0,"threePointersAttempted":0,"threePointersMade":0,"threePointersPercentage":0.0,"turnovers":0,"twoPointersAttempted":0,"twoPointersMade":0,"twoPointersPercentage":0.0},"name":"Ed Davis","nameI":"E. Davis","firstName":"Ed","familyName":"Davis"},{"status":"ACTIVE","order":13,"personId":1629020,"jerseyNum":"8","starter":"0","oncourt":"0","played":"0","statistics":{"assists":0,"blocks":0,"blocksReceived":0,"fieldGoalsAttempted":0,"fieldGoalsMade":0,"fieldGoalsPercentage":0.0,"foulsOffensive":0,"foulsDrawn":0,"foulsPersonal":0,"foulsTechnical":0,"freeThrowsAttempted":0,"freeThrowsMade":0,"freeThrowsPercentage":0.0,"minus":0.0,"minutes":"PT00M00.00S","minutesCalculated":"PT00M","plus":0.0,"plusMinusPoints":0.0,"points":0,"pointsFastBreak":0,"pointsInThePaint":0,"pointsSecondChance":0,"reboundsDefensive":0,"reboundsOffensive":0,"reboundsTotal":0,"steals":0,"threePointersAttempted":0,"threePointersMade":0,"threePointersPercentage":0.0,"turnovers":0,"twoPointersAttempted":0,"twoPointersMade":0,"twoPointersPercentage":0.0},"name":"Jarred Vanderbilt","nameI":"J. Vanderbilt","firstName":"Jarred","familyName":"Vanderbilt"},{"status":"INACTIVE","notPlayingReason":"INACTIVE_INJURY","notPlayingDescription":"Left Hamstring; Injury","order":14,"personId":1627736,"jerseyNum":"5","starter":"0","oncourt":"0","played":"0","statistics":{"assists":0,"blocks":0,"blocksReceived":0,"fieldGoalsAttempted":0,"fieldGoalsMade":0,"fieldGoalsPercentage":0.0,"foulsOffensive":0,"foulsDrawn":0,"foulsPersonal":0,"foulsTechnical":0,"freeThrowsAttempted":0,"freeThrowsMade":0,"freeThrowsPercentage":0.0,"minus":0.0,"minutes":"PT00M00.00S","minutesCalculated":"PT00M","plus":0.0,"plusMinusPoints":0.0,"points":0,"pointsFastBreak":0,"pointsInThePaint":0,"pointsSecondChance":0,"reboundsDefensive":0,"reboundsOffensive":0,"reboundsTotal":0,"steals":0,"threePointersAttempted":0,"threePointersMade":0,"threePointersPercentage":0.0,"turnovers":0,"twoPointersAttempted":0,"twoPointersMade":0,"twoPointersPercentage":0.0},"name":"Malik Beasley","nameI":"M. Beasley","firstName":"Malik","familyName":"Beasley"},{"status":"INACTIVE","notPlayingReason":"INACTIVE_INJURY","notPlayingDescription":"Right Tibia; Contusion","order":15,"personId":1629669,"jerseyNum":"4","starter":"0","oncourt":"0","played":"0","statistics":{"assists":0,"blocks":0,"blocksReceived":0,"fieldGoalsAttempted":0,"fieldGoalsMade":0,"fieldGoalsPercentage":0.0,"foulsOffensive":0,"foulsDrawn":0,"foulsPersonal":0,"foulsTechnical":0,"freeThrowsAttempted":0,"freeThrowsMade":0,"freeThrowsPercentage":0.0,"minus":0.0,"minutes":"PT00M00.00S","minutesCalculated":"PT00M","plus":0.0,"plusMinusPoints":0.0,"points":0,"pointsFastBreak":0,"pointsInThePaint":0,"pointsSecondChance":0,"reboundsDefensive":0,"reboundsOffensive":0,"reboundsTotal":0,"steals":0,"threePointersAttempted":0,"threePointersMade":0,"threePointersPercentage":0.0,"turnovers":0,"twoPointersAttempted":0,"twoPointersMade":0,"twoPointersPercentage":0.0},"name":"Jaylen Nowell","nameI":"J. Nowell","firstName":"Jaylen","familyName":"Nowell"}],"statistics":{"assists":22,"assistsTurnoverRatio":1.57142857142857,"benchPoints":60,"biggestLead":11,"biggestLeadScore":"93-104","biggestScoringRun":12,"biggestScoringRunScore":"93-104","blocks":4,"blocksReceived":8,"fastBreakPointsAttempted":6,"fastBreakPointsMade":4,"fastBreakPointsPercentage":0.666666666666666,"fieldGoalsAttempted":91,"fieldGoalsEffectiveAdjusted":0.483516483516484,"fieldGoalsMade":38,"fieldGoalsPercentage":0.41758241758241804,"foulsOffensive":1,"foulsDrawn":19,"foulsPersonal":16,"foulsTeam":15,"foulsTechnical":0,"foulsTeamTechnical":1,"freeThrowsAttempted":33,"freeThrowsMade":28,"freeThrowsPercentage":0.8484848484848481,"leadChanges":8,"minutes":"PT240M00.00S","minutesCalculated":"PT240M","points":116,"pointsAgainst":106,"pointsFastBreak":12,"pointsFromTurnovers":13,"pointsInThePaint":46,"pointsInThePaintAttempted":46,"pointsInThePaintMade":23,"pointsInThePaintPercentage":0.5,"pointsSecondChance":13,"reboundsDefensive":36,"reboundsOffensive":15,"reboundsPersonal":51,"reboundsTeam":11,"reboundsTeamDefensive":3,"reboundsTeamOffensive":8,"reboundsTotal":62,"secondChancePointsAttempted":14,"secondChancePointsMade":5,"secondChancePointsPercentage":0.357142857142857,"steals":10,"threePointersAttempted":32,"threePointersMade":12,"threePointersPercentage":0.375,"timeLeading":"PT19M31.96S","timesTied":14,"trueShootingAttempts":105.52,"trueShootingPercentage":0.549658832448825,"turnovers":14,"turnoversTeam":0,"turnoversTotal":14,"twoPointersAttempted":59,"twoPointersMade":26,"twoPointersPercentage":0.440677966101695}},"awayTeam":{"teamId":1610612758,"teamName":"Kings","teamCity":"Sacramento","teamTricode":"SAC","score":106,"inBonus":"0","timeoutsRemaining":1,"periods":[{"period":1,"periodType":"REGULAR","score":29},{"period":2,"periodType":"REGULAR","score":26},{"period":3,"periodType":"REGULAR","score":27},{"period":4,"periodType":"REGULAR","score":24}],"players":[{"status":"ACTIVE","order":1,"personId":1627741,"jerseyNum":"24","position":"SF","starter":"1","oncourt":"1","played":"1","statistics":{"assists":3,"blocks":1,"blocksReceived":0,"fieldGoalsAttempted":17,"fieldGoalsMade":6,"fieldGoalsPercentage":0.352941176470588,"foulsOffensive":0,"foulsDrawn":0,"foulsPersonal":2,"foulsTechnical":0,"freeThrowsAttempted":0,"freeThrowsMade":0,"freeThrowsPercentage":0.0,"minus":82.0,"minutes":"PT32M22.00S","minutesCalculated":"PT32M","plus":80.0,"plusMinusPoints":-2.0,"points":18,"pointsFastBreak":0,"pointsInThePaint":0,"pointsSecondChance":9,"reboundsDefensive":7,"reboundsOffensive":0,"reboundsTotal":7,"steals":2,"threePointersAttempted":16,"threePointersMade":6,"threePointersPercentage":0.375,"turnovers":3,"twoPointersAttempted":1,"twoPointersMade":0,"twoPointersPercentage":0.0},"name":"Buddy Hield","nameI":"B. Hield","firstName":"Buddy","familyName":"Hield"},{"status":"ACTIVE","order":2,"personId":203084,"jerseyNum":"40","position":"PF","starter":"1","oncourt":"1","played":"1","statistics":{"assists":4,"blocks":0,"blocksReceived":0,"fieldGoalsAttempted":14,"fieldGoalsMade":9,"fieldGoalsPercentage":0.642857142857143,"foulsOffensive":0,"foulsDrawn":3,"foulsPersonal":1,"foulsTechnical":0,"freeThrowsAttempted":4,"freeThrowsMade":3,"freeThrowsPercentage":0.75,"minus":92.0,"minutes":"PT37M22.00S","minutesCalculated":"PT37M","plus":89.0,"plusMinusPoints":-3.0,"points":21,"pointsFastBreak":2,"pointsInThePaint":16,"pointsSecondChance":4,"reboundsDefensive":9,"reboundsOffensive":3,"reboundsTotal":12,"steals":1,"threePointersAttempted":3,"threePointersMade":0,"threePointersPercentage":0.0,"turnovers":2,"twoPointersAttempted":11,"twoPointersMade":9,"twoPointersPercentage":0.818181818181818},"name":"Harrison Barnes","nameI":"H. Barnes","firstName":"Harrison","familyName":"Barnes"},{"status":"ACTIVE","order":3,"personId":1626158,"jerseyNum":"22","position":"C","starter":"1","oncourt":"1","played":"1","statistics":{"assists":2,"blocks":3,"blocksReceived":0,"fieldGoalsAttempted":10,"fieldGoalsMade":5,"fieldGoalsPercentage":0.5,"foulsOffensive":0,"foulsDrawn":2,"foulsPersonal":4,"foulsTechnical":0,"freeThrowsAttempted":2,"freeThrowsMade":1,"freeThrowsPercentage":0.5,"minus":88.0,"minutes":"PT34M49.00S","minutesCalculated":"PT35M","plus":87.0,"plusMinusPoints":-1.0,"points":11,"pointsFastBreak":2,"pointsInThePaint":8,"pointsSecondChance":0,"reboundsDefensive":3,"reboundsOffensive":3,"reboundsTotal":6,"steals":1,"threePointersAttempted":1,"threePointersMade":0,"threePointersPercentage":0.0,"turnovers":0,"twoPointersAttempted":9,"twoPointersMade":5,"twoPointersPercentage":0.555555555555556},"name":"Richaun Holmes","nameI":"R. Holmes","firstName":"Richaun","familyName":"Holmes"},{"status":"ACTIVE","order":4,"personId":1630169,"jerseyNum":"0","position":"SG","starter":"1","oncourt":"1","played":"1","statistics":{"assists":7,"blocks":2,"blocksReceived":1,"fieldGoalsAttempted":9,"fieldGoalsMade":4,"fieldGoalsPercentage":0.444444444444444,"foulsOffensive":0,"foulsDrawn":1,"foulsPersonal":2,"foulsTechnical":0,"freeThrowsAttempted":1,"freeThrowsMade":1,"freeThrowsPercentage":1.0,"minus":73.0,"minutes":"PT33M18.00S","minutesCalculated":"PT33M","plus":82.0,"plusMinusPoints":9.0,"points":9,"pointsFastBreak":4,"pointsInThePaint":6,"pointsSecondChance":0,"reboundsDefensive":1,"reboundsOffensive":1,"reboundsTotal":2,"steals":2,"threePointersAttempted":2,"threePointersMade":0,"threePointersPercentage":0.0,"turnovers":1,"twoPointersAttempted":7,"twoPointersMade":4,"twoPointersPercentage":0.5714285714285711},"name":"Tyrese Haliburton","nameI":"T. Haliburton","firstName":"Tyrese","familyName":"Haliburton"},{"status":"ACTIVE","order":5,"personId":1628368,"jerseyNum":"5","position":"PG","starter":"1","oncourt":"1","played":"1","statistics":{"assists":9,"blocks":0,"blocksReceived":1,"fieldGoalsAttempted":16,"fieldGoalsMade":8,"fieldGoalsPercentage":0.5,"foulsOffensive":0,"foulsDrawn":8,"foulsPersonal":3,"foulsTechnical":0,"freeThrowsAttempted":15,"freeThrowsMade":13,"freeThrowsPercentage":0.866666666666667,"minus":93.0,"minutes":"PT37M30.00S","minutesCalculated":"PT38M","plus":87.0,"plusMinusPoints":-6.0,"points":31,"pointsFastBreak":5,"pointsInThePaint":10,"pointsSecondChance":0,"reboundsDefensive":5,"reboundsOffensive":1,"reboundsTotal":6,"steals":2,"threePointersAttempted":4,"threePointersMade":2,"threePointersPercentage":0.5,"turnovers":4,"twoPointersAttempted":12,"twoPointersMade":6,"twoPointersPercentage":0.5},"name":"De'Aaron Fox","nameI":"D. Fox","firstName":"De'Aaron","familyName":"Fox"},{"status":"ACTIVE","order":6,"personId":1626153,"jerseyNum":"55","starter":"0","oncourt":"0","played":"1","statistics":{"assists":1,"blocks":0,"blocksReceived":0,"fieldGoalsAttempted":7,"fieldGoalsMade":2,"fieldGoalsPercentage":0.28571428571428603,"foulsOffensive":0,"foulsDrawn":1,"foulsPersonal":1,"foulsTechnical":0,"freeThrowsAttempted":0,"freeThrowsMade":0,"freeThrowsPercentage":0.0,"minus":45.0,"minutes":"PT19M37.00S","minutesCalculated":"PT20M","plus":37.0,"plusMinusPoints":-8.0,"points":4,"pointsFastBreak":2,"pointsInThePaint":4,"pointsSecondChance":0,"reboundsDefensive":1,"reboundsOffensive":1,"reboundsTotal":2,"steals":0,"threePointersAttempted":4,"threePointersMade":0,"threePointersPercentage":0.0,"turnovers":3,"twoPointersAttempted":3,"twoPointersMade":2,"twoPointersPercentage":0.666666666666666},"name":"Delon Wright","nameI":"D. Wright","firstName":"Delon","familyName":"Wright"},{"status":"ACTIVE","order":7,"personId":1629056,"jerseyNum":"9","starter":"0","oncourt":"0","played":"1","statistics":{"assists":0,"blocks":0,"blocksReceived":1,"fieldGoalsAttempted":8,"fieldGoalsMade":1,"fieldGoalsPercentage":0.125,"foulsOffensive":0,"foulsDrawn":0,"foulsPersonal":2,"foulsTechnical":1,"freeThrowsAttempted":0,"freeThrowsMade":0,"freeThrowsPercentage":0.0,"minus":42.0,"minutes":"PT17M36.00S","minutesCalculated":"PT18M","plus":26.0,"plusMinusPoints":-16.0,"points":3,"pointsFastBreak":0,"pointsInThePaint":0,"pointsSecondChance":0,"reboundsDefensive":1,"reboundsOffensive":0,"reboundsTotal":1,"steals":0,"threePointersAttempted":6,"threePointersMade":1,"threePointersPercentage":0.166666666666667,"turnovers":0,"twoPointersAttempted":2,"twoPointersMade":0,"twoPointersPercentage":0.0},"name":"Terence Davis","nameI":"T. Davis","firstName":"Terence","familyName":"Davis"},{"status":"ACTIVE","order":8,"personId":203090,"jerseyNum":"8","starter":"0","oncourt":"0","played":"1","statistics":{"assists":1,"blocks":1,"blocksReceived":0,"fieldGoalsAttempted":1,"fieldGoalsMade":1,"fieldGoalsPercentage":1.0,"foulsOffensive":0,"foulsDrawn":0,"foulsPersonal":4,"foulsTechnical":0,"freeThrowsAttempted":0,"freeThrowsMade":0,"freeThrowsPercentage":0.0,"minus":37.0,"minutes":"PT14M15.00S","minutesCalculated":"PT14M","plus":23.0,"plusMinusPoints":-14.0,"points":2,"pointsFastBreak":0,"pointsInThePaint":2,"pointsSecondChance":0,"reboundsDefensive":1,"reboundsOffensive":0,"reboundsTotal":1,"steals":0,"threePointersAttempted":0,"threePointersMade":0,"threePointersPercentage":0.0,"turnovers":0,"twoPointersAttempted":1,"twoPointersMade":1,"twoPointersPercentage":1.0},"name":"Maurice Harkless","nameI":"M. Harkless","firstName":"Maurice","familyName":"Harkless"},{"status":"ACTIVE","order":9,"personId":202355,"jerseyNum":"20","starter":"0","oncourt":"0","played":"1","statistics":{"assists":0,"blocks":1,"blocksReceived":1,"fieldGoalsAttempted":6,"fieldGoalsMade":3,"fieldGoalsPercentage":0.5,"foulsOffensive":0,"foulsDrawn":1,"foulsPersonal":0,"foulsTechnical":0,"freeThrowsAttempted":2,"freeThrowsMade":1,"freeThrowsPercentage":0.5,"minus":28.0,"minutes":"PT13M11.00S","minutesCalculated":"PT13M","plus":19.0,"plusMinusPoints":-9.0,"points":7,"pointsFastBreak":0,"pointsInThePaint":6,"pointsSecondChance":0,"reboundsDefensive":4,"reboundsOffensive":1,"reboundsTotal":5,"steals":1,"threePointersAttempted":0,"threePointersMade":0,"threePointersPercentage":0.0,"turnovers":1,"twoPointersAttempted":6,"twoPointersMade":3,"twoPointersPercentage":0.5},"name":"Hassan Whiteside","nameI":"H. Whiteside","firstName":"Hassan","familyName":"Whiteside"},{"status":"ACTIVE","order":10,"personId":1629657,"jerseyNum":"7","starter":"0","oncourt":"0","played":"0","statistics":{"assists":0,"blocks":0,"blocksReceived":0,"fieldGoalsAttempted":0,"fieldGoalsMade":0,"fieldGoalsPercentage":0.0,"foulsOffensive":0,"foulsDrawn":0,"foulsPersonal":0,"foulsTechnical":0,"freeThrowsAttempted":0,"freeThrowsMade":0,"freeThrowsPercentage":0.0,"minus":0.0,"minutes":"PT00M00.00S","minutesCalculated":"PT00M","plus":0.0,"plusMinusPoints":0.0,"points":0,"pointsFastBreak":0,"pointsInThePaint":0,"pointsSecondChance":0,"reboundsDefensive":0,"reboundsOffensive":0,"reboundsTotal":0,"steals":0,"threePointersAttempted":0,"threePointersMade":0,"threePointersPercentage":0.0,"turnovers":0,"twoPointersAttempted":0,"twoPointersMade":0,"twoPointersPercentage":0.0},"name":"Kyle Guy","nameI":"K. Guy","firstName":"Kyle","familyName":"Guy"},{"status":"ACTIVE","order":11,"personId":1629713,"jerseyNum":"10","starter":"0","oncourt":"0","played":"0","statistics":{"assists":0,"blocks":0,"blocksReceived":0,"fieldGoalsAttempted":0,"fieldGoalsMade":0,"fieldGoalsPercentage":0.0,"foulsOffensive":0,"foulsDrawn":0,"foulsPersonal":0,"foulsTechnical":0,"freeThrowsAttempted":0,"freeThrowsMade":0,"freeThrowsPercentage":0.0,"minus":0.0,"minutes":"PT00M00.00S","minutesCalculated":"PT00M","plus":0.0,"plusMinusPoints":0.0,"points":0,"pointsFastBreak":0,"pointsInThePaint":0,"pointsSecondChance":0,"reboundsDefensive":0,"reboundsOffensive":0,"reboundsTotal":0,"steals":0,"threePointersAttempted":0,"threePointersMade":0,"threePointersPercentage":0.0,"turnovers":0,"twoPointersAttempted":0,"twoPointersMade":0,"twoPointersPercentage":0.0},"name":"Justin James","nameI":"J. James","firstName":"Justin","familyName":"James"},{"status":"ACTIVE","order":12,"personId":1629002,"jerseyNum":"25","starter":"0","oncourt":"0","played":"0","statistics":{"assists":0,"blocks":0,"blocksReceived":0,"fieldGoalsAttempted":0,"fieldGoalsMade":0,"fieldGoalsPercentage":0.0,"foulsOffensive":0,"foulsDrawn":0,"foulsPersonal":0,"foulsTechnical":0,"freeThrowsAttempted":0,"freeThrowsMade":0,"freeThrowsPercentage":0.0,"minus":0.0,"minutes":"PT00M00.00S","minutesCalculated":"PT00M","plus":0.0,"plusMinusPoints":0.0,"points":0,"pointsFastBreak":0,"pointsInThePaint":0,"pointsSecondChance":0,"reboundsDefensive":0,"reboundsOffensive":0,"reboundsTotal":0,"steals":0,"threePointersAttempted":0,"threePointersMade":0,"threePointersPercentage":0.0,"turnovers":0,"twoPointersAttempted":0,"twoPointersMade":0,"twoPointersPercentage":0.0},"name":"Chimezie Metu","nameI":"C. Metu","firstName":"Chimezie","familyName":"Metu"},{"status":"ACTIVE","order":13,"personId":1629735,"jerseyNum":"30","starter":"0","oncourt":"0","played":"0","statistics":{"assists":0,"blocks":0,"blocksReceived":0,"fieldGoalsAttempted":0,"fieldGoalsMade":0,"fieldGoalsPercentage":0.0,"foulsOffensive":0,"foulsDrawn":0,"foulsPersonal":0,"foulsTechnical":0,"freeThrowsAttempted":0,"freeThrowsMade":0,"freeThrowsPercentage":0.0,"minus":0.0,"minutes":"PT00M00.00S","minutesCalculated":"PT00M","plus":0.0,"plusMinusPoints":0.0,"points":0,"pointsFastBreak":0,"pointsInThePaint":0,"pointsSecondChance":0,"reboundsDefensive":0,"reboundsOffensive":0,"reboundsTotal":0,"steals":0,"threePointersAttempted":0,"threePointersMade":0,"threePointersPercentage":0.0,"turnovers":0,"twoPointersAttempted":0,"twoPointersMade":0,"twoPointersPercentage":0.0},"name":"Chris Silva","nameI":"C. Silva","firstName":"Chris","familyName":"Silva"},{"status":"ACTIVE","order":14,"personId":1630218,"jerseyNum":"13","starter":"0","oncourt":"0","played":"0","statistics":{"assists":0,"blocks":0,"blocksReceived":0,"fieldGoalsAttempted":0,"fieldGoalsMade":0,"fieldGoalsPercentage":0.0,"foulsOffensive":0,"foulsDrawn":0,"foulsPersonal":0,"foulsTechnical":0,"freeThrowsAttempted":0,"freeThrowsMade":0,"freeThrowsPercentage":0.0,"minus":0.0,"minutes":"PT00M00.00S","minutesCalculated":"PT00M","plus":0.0,"plusMinusPoints":0.0,"points":0,"pointsFastBreak":0,"pointsInThePaint":0,"pointsSecondChance":0,"reboundsDefensive":0,"reboundsOffensive":0,"reboundsTotal":0,"steals":0,"threePointersAttempted":0,"threePointersMade":0,"threePointersPercentage":0.0,"turnovers":0,"twoPointersAttempted":0,"twoPointersMade":0,"twoPointersPercentage":0.0},"name":"Robert Woodard II","nameI":"R. Woodard II","firstName":"Robert","familyName":"Woodard II"},{"status":"INACTIVE","notPlayingReason":"INACTIVE_INJURY","notPlayingDescription":"Left 4th Metacarpal; Fracture ","order":15,"personId":1628963,"jerseyNum":"35","starter":"0","oncourt":"0","played":"0","statistics":{"assists":0,"blocks":0,"blocksReceived":0,"fieldGoalsAttempted":0,"fieldGoalsMade":0,"fieldGoalsPercentage":0.0,"foulsOffensive":0,"foulsDrawn":0,"foulsPersonal":0,"foulsTechnical":0,"freeThrowsAttempted":0,"freeThrowsMade":0,"freeThrowsPercentage":0.0,"minus":0.0,"minutes":"PT00M00.00S","minutesCalculated":"PT00M","plus":0.0,"plusMinusPoints":0.0,"points":0,"pointsFastBreak":0,"pointsInThePaint":0,"pointsSecondChance":0,"reboundsDefensive":0,"reboundsOffensive":0,"reboundsTotal":0,"steals":0,"threePointersAttempted":0,"threePointersMade":0,"threePointersPercentage":0.0,"turnovers":0,"twoPointersAttempted":0,"twoPointersMade":0,"twoPointersPercentage":0.0},"name":"Marvin Bagley III","nameI":"M. Bagley III","firstName":"Marvin","familyName":"Bagley III"},{"status":"INACTIVE","notPlayingReason":"INACTIVE_COACH","order":16,"personId":1630186,"jerseyNum":"3","starter":"0","oncourt":"0","played":"0","statistics":{"assists":0,"blocks":0,"blocksReceived":0,"fieldGoalsAttempted":0,"fieldGoalsMade":0,"fieldGoalsPercentage":0.0,"foulsOffensive":0,"foulsDrawn":0,"foulsPersonal":0,"foulsTechnical":0,"freeThrowsAttempted":0,"freeThrowsMade":0,"freeThrowsPercentage":0.0,"minus":0.0,"minutes":"PT00M00.00S","minutesCalculated":"PT00M","plus":0.0,"plusMinusPoints":0.0,"points":0,"pointsFastBreak":0,"pointsInThePaint":0,"pointsSecondChance":0,"reboundsDefensive":0,"reboundsOffensive":0,"reboundsTotal":0,"steals":0,"threePointersAttempted":0,"threePointersMade":0,"threePointersPercentage":0.0,"turnovers":0,"twoPointersAttempted":0,"twoPointersMade":0,"twoPointersPercentage":0.0},"name":"Jahmi'us Ramsey","nameI":"J. Ramsey","firstName":"Jahmi'us","familyName":"Ramsey"}],"statistics":{"assists":27,"assistsTurnoverRatio":1.8,"benchPoints":16,"biggestLead":8,"biggestLeadScore":"80-72","biggestScoringRun":12,"biggestScoringRunScore":"93-104","blocks":8,"blocksReceived":4,"fastBreakPointsAttempted":7,"fastBreakPointsMade":5,"fastBreakPointsPercentage":0.714285714285714,"fieldGoalsAttempted":88,"fieldGoalsEffectiveAdjusted":0.494318181818182,"fieldGoalsMade":39,"fieldGoalsPercentage":0.443181818181818,"foulsOffensive":0,"foulsDrawn":16,"foulsPersonal":19,"foulsTeam":19,"foulsTechnical":1,"foulsTeamTechnical":0,"freeThrowsAttempted":24,"freeThrowsMade":19,"freeThrowsPercentage":0.791666666666666,"leadChanges":8,"minutes":"PT240M00.00S","minutesCalculated":"PT240M","points":106,"pointsAgainst":116,"pointsFastBreak":15,"pointsFromTurnovers":21,"pointsInThePaint":52,"pointsInThePaintAttempted":43,"pointsInThePaintMade":26,"pointsInThePaintPercentage":0.604651162790698,"pointsSecondChance":13,"reboundsDefensive":32,"reboundsOffensive":10,"reboundsPersonal":42,"reboundsTeam":8,"reboundsTeamDefensive":3,"reboundsTeamOffensive":5,"reboundsTotal":50,"secondChancePointsAttempted":8,"secondChancePointsMade":5,"secondChancePointsPercentage":0.625,"steals":9,"threePointersAttempted":36,"threePointersMade":9,"threePointersPercentage":0.25,"timeLeading":"PT21M20.94S","timesTied":14,"trueShootingAttempts":98.56,"trueShootingPercentage":0.537743506493506,"turnovers":14,"turnoversTeam":1,"turnoversTotal":15,"twoPointersAttempted":52,"twoPointersMade":30,"twoPointersPercentage":0.576923076923077}}}}